Metadata-Version: 2.1
Name: aka-mlearning
Version: 0.0.2
Summary: Regression and classification analysis tools
Author: Kader Geraldo
